awesome_hello/__init__.py
awesome_hello/main.py
awesome_hello/py.typed
awesome_hello-0.2.1.dist-info/METADATA
awesome_hello-0.2.1.dist-info/WHEEL
awesome_hello-0.2.1.dist-info/licenses/LICENSE
awesome_hello-0.2.1.dist-info/licenses/LICENSE copy
awesome_hello-0.2.1.dist-info/RECORD
