Metadata-Version: 2.4
Name: awesome-hello
Version: 0.2.1
Summary: Add your description here
License-File: LICENSE
License-File: LICENSE copy
Requires-Python: >=3.11
Requires-Dist: bolt-agent-toolkit>=0.1.0
Requires-Dist: requests>=2.32.4
